nomad_camels_driver_keysight_b2912a/keysight_b2912a.py
nomad_camels_driver_keysight_b2912a/keysight_b2912a_channel_config.py
nomad_camels_driver_keysight_b2912a/keysight_b2912a_config.py
nomad_camels_driver_keysight_b2912a/keysight_b2912a_ophyd.py
nomad_camels_driver_keysight_b2912a-0.1.2.dist-info/licenses/LICENSE.txt
nomad_camels_driver_keysight_b2912a-0.1.2.dist-info/METADATA
nomad_camels_driver_keysight_b2912a-0.1.2.dist-info/WHEEL
nomad_camels_driver_keysight_b2912a-0.1.2.dist-info/top_level.txt
nomad_camels_driver_keysight_b2912a-0.1.2.dist-info/RECORD
